pytestapilib/__init__.py
pytestapilib/core/__init__.py
pytestapilib/core/config.py
pytestapilib/core/file.py
pytestapilib/core/log.py
pytestapilib/core/system.py
pytestapilib/core/version.py
pytestapilib/http/__init__.py
pytestapilib/http/base.py
pytestapilib/http/builder.py
pytestapilib/http/enum.py
pytestapilib/http/log.py
pytestapilib-1.4.0.dist-info/METADATA
pytestapilib-1.4.0.dist-info/WHEEL
pytestapilib-1.4.0.dist-info/top_level.txt
pytestapilib-1.4.0.dist-info/RECORD
